cdk_cloudformation_mongodb_atlas_databaseuser/__init__.py
cdk_cloudformation_mongodb_atlas_databaseuser/py.typed
cdk_cloudformation_mongodb_atlas_databaseuser/_jsii/__init__.py
cdk_cloudformation_mongodb_atlas_databaseuser/_jsii/mongodb-atlas-databaseuser@1.3.0-alpha.7.jsii.tgz
cdk_cloudformation_mongodb_atlas_databaseuser-1.3.0a7.dist-info/LICENSE
cdk_cloudformation_mongodb_atlas_databaseuser-1.3.0a7.dist-info/METADATA
cdk_cloudformation_mongodb_atlas_databaseuser-1.3.0a7.dist-info/WHEEL
cdk_cloudformation_mongodb_atlas_databaseuser-1.3.0a7.dist-info/top_level.txt
cdk_cloudformation_mongodb_atlas_databaseuser-1.3.0a7.dist-info/RECORD
