Metadata-Version: 2.1
Name: cdk-cloudformation-mongodb-atlas-databaseuser
Version: 1.3.0a7
Summary: The databaseUsers resource lets you retrieve, create and modify the MongoDB users in your cluster. Each user has a set of roles that provide access to the project?s databases. A user?s roles apply to all the clusters in the project: if two clusters have a products database and a user has a role granting read access on the products database, the user has that access on both clusters.
Home-page: https://github.com/cdklabs/cdk-cloudformation.git
Author: Amazon Web Services
License: Apache-2.0
Project-URL: Source, https://github.com/cdklabs/cdk-cloudformation.git
Platform: UNKNOWN
Classifier: Intended Audience :: Developers
Classifier: Operating System :: OS Independent
Classifier: Programming Language :: JavaScript
Classifier: Programming Language :: Python :: 3 :: Only
Classifier: Programming Language :: Python :: 3.7
Classifier: Programming Language :: Python :: 3.8
Classifier: Programming Language :: Python :: 3.9
Classifier: Programming Language :: Python :: 3.10
Classifier: Typing :: Typed
Classifier: Development Status :: 7 - Inactive
Classifier: License :: OSI Approved
Requires-Python: ~=3.7
License-File: LICENSE
Requires-Dist: aws-cdk-lib (<3.0.0,>=2.63.0)
Requires-Dist: constructs (<11.0.0,>=10.1.239)
Requires-Dist: jsii (<2.0.0,>=1.74.0)
Requires-Dist: publication (>=0.0.3)
Requires-Dist: typeguard (~=2.13.3)
